CHANGES.txt
LICENSE.txt
MANIFEST.in
README.txt
setup.py
docs/Makefile
docs/conf.py
docs/index.rst
docs/make.bat
pyramid_assetviews/__init__.py
pyramid_assetviews/tests.py
pyramid_assetviews.egg-info/PKG-INFO
pyramid_assetviews.egg-info/SOURCES.txt
pyramid_assetviews.egg-info/dependency_links.txt
pyramid_assetviews.egg-info/not-zip-safe
pyramid_assetviews.egg-info/requires.txt
pyramid_assetviews.egg-info/top_level.txt
pyramid_assetviews/test_assets/crossdomain.xml
pyramid_assetviews/test_assets/favicon.ico
pyramid_assetviews/test_assets/nomimetype
pyramid_assetviews/test_assets/robots.txt