Metadata-Version: 1.0
Name: pyramid-assetviews
Version: 1.0a3
Summary: pyramid_assetviews
Home-page: https://github.com/nek4life/pyramid_assetviews
Author: Charlie Choiniere
Author-email: pylons-discuss@googlegroups.com
License: UNKNOWN
Keywords: pyramid
Platform: UNKNOWN
Classifier: Programming Language :: Python
